llama_index/readers/gitbook/__init__.py
llama_index/readers/gitbook/base.py
llama_index/readers/gitbook/gitbook_client.py
llama_index_readers_gitbook-0.4.1.dist-info/METADATA
llama_index_readers_gitbook-0.4.1.dist-info/WHEEL
llama_index_readers_gitbook-0.4.1.dist-info/licenses/LICENSE
llama_index_readers_gitbook-0.4.1.dist-info/RECORD
