Metadata-Version: 2.4
Name: llama-index-readers-gitbook
Version: 0.4.1
Summary: llama-index readers gitbook integration
Author-email: "thomas.kang" <mc.kang08@gmail.com>
Maintainer: mckang
License-Expression: MIT
License-File: LICENSE
Keywords: gitbook
Requires-Python: <4.0,>=3.9
Requires-Dist: llama-index-core<0.15,>=0.13.0
Requires-Dist: pymongo<5,>=4.6.1
